wg_web_autoclient/__init__.py
wg_web_autoclient/client.py
wg_web_autoclient/driver_factory.py
wg_web_autoclient/exceptions.py
wg_web_autoclient-0.1.0.dist-info/licenses/LICENSE
wg_web_autoclient-0.1.0.dist-info/METADATA
wg_web_autoclient-0.1.0.dist-info/WHEEL
wg_web_autoclient-0.1.0.dist-info/top_level.txt
wg_web_autoclient-0.1.0.dist-info/RECORD
