Metadata-Version: 2.4
Name: wg_web_autoclient
Version: 0.1.0
Summary: WireGuard automation client with async support using Selenium and aiohttp
Home-page: https://github.com/Zurlex/wg_client_work
Author: Zurlex
Author-email: your_email@example.com
License: MIT
Classifier: License :: OSI Approved :: MIT License
Classifier: Programming Language :: Python :: 3
Classifier: Programming Language :: Python :: 3.8
Classifier: Operating System :: OS Independent
Classifier: Development Status :: 3 - Alpha
Classifier: Topic :: Internet :: Proxy Servers
Classifier: Topic :: System :: Networking
Requires-Python: >=3.8
License-File: LICENSE
Requires-Dist: selenium>=4.0.0
Requires-Dist: webdriver-manager>=4.0.0
Requires-Dist: aiohttp>=3.8.0
Dynamic: author
Dynamic: author-email
Dynamic: classifier
Dynamic: home-page
Dynamic: license
Dynamic: license-file
Dynamic: requires-dist
Dynamic: requires-python
Dynamic: summary
